figur/__init__.py
figur/api.py
figur/model.py
figur/utils.py
figur/zenodo.py
figur-0.0.6.dist-info/LICENSE
figur-0.0.6.dist-info/METADATA
figur-0.0.6.dist-info/WHEEL
figur-0.0.6.dist-info/top_level.txt
figur-0.0.6.dist-info/RECORD
