Metadata-Version: 2.1
Name: figur
Version: 0.0.6
Summary: Figurenerkennung for German literary texts
Home-page: https://github.com/severinsimmler/figur
Author: Severin Simmler
License: MIT
Platform: UNKNOWN
Classifier: License :: OSI Approved :: MIT License
Classifier: Programming Language :: Python
Classifier: Programming Language :: Python :: 3
Classifier: Programming Language :: Python :: 3.6
Classifier: Programming Language :: Python :: 3.7
Classifier: Programming Language :: Python :: Implementation :: CPython
Classifier: Programming Language :: Python :: Implementation :: PyPy
Requires-Python: >=3.6.0
Requires-Dist: flair (>=0.4.1)
Requires-Dist: spacy (>=2.0.18)
Requires-Dist: pandas (>=0.24.1)
Requires-Dist: wget (>=3.2)
Requires-Dist: requests (>=2.21.0)
